rsync_system_backup/__init__.py
rsync_system_backup/cli.py
rsync_system_backup/destinations.py
rsync_system_backup/exceptions.py
rsync_system_backup/tests.py
rsync_system_backup-1.1.dist-info/LICENSE.txt
rsync_system_backup-1.1.dist-info/METADATA
rsync_system_backup-1.1.dist-info/WHEEL
rsync_system_backup-1.1.dist-info/entry_points.txt
rsync_system_backup-1.1.dist-info/top_level.txt
rsync_system_backup-1.1.dist-info/RECORD
