Metadata-Version: 2.1
Name: rsync-system-backup
Version: 1.1
Summary: Linux system backups powered by rsync
Home-page: https://github.com/xolox/python-rsync-system-backup
Author: Peter Odding
Author-email: peter@peterodding.com
License: UNKNOWN
Platform: UNKNOWN
Classifier: Development Status :: 4 - Beta
Classifier: Environment :: Console
Classifier: Intended Audience :: Developers
Classifier: Intended Audience :: System Administrators
Classifier: License :: OSI Approved :: MIT License
Classifier: Operating System :: POSIX :: Linux
Classifier: Programming Language :: Python
Classifier: Programming Language :: Python :: 2
Classifier: Programming Language :: Python :: 2.7
Classifier: Programming Language :: Python :: 3
Classifier: Programming Language :: Python :: 3.4
Classifier: Programming Language :: Python :: 3.5
Classifier: Programming Language :: Python :: 3.6
Classifier: Programming Language :: Python :: 3.7
Classifier: Programming Language :: Python :: Implementation :: CPython
Classifier: Programming Language :: Python :: Implementation :: PyPy
Classifier: Topic :: Software Development
Classifier: Topic :: Software Development :: Libraries :: Python Modules
Classifier: Topic :: System :: Archiving :: Backup
Classifier: Topic :: System :: Systems Administration
Requires-Dist: coloredlogs (>=6.1)
Requires-Dist: executor (>=19.3)
Requires-Dist: humanfriendly (>=3.4)
Requires-Dist: linux-utils (>=0.4)
Requires-Dist: proc (>=0.14)
Requires-Dist: property-manager (>=2.3)
Requires-Dist: rotate-backups (>=4.4)
